jucycru/__init__.py
jucycru/jucycru.py
jucycru/examples/GTplus.py
jucycru/examples/GroundTrack.py
jucycru/examples/angleExampleScript.py
jucycru/examples/distExampleScript.py
jucycru/surfaces/earth.png
jucycru-0.4.2.data/scripts/distExampleScript.py
jucycru-0.4.2.dist-info/DESCRIPTION.rst
jucycru-0.4.2.dist-info/METADATA
jucycru-0.4.2.dist-info/RECORD
jucycru-0.4.2.dist-info/WHEEL
jucycru-0.4.2.dist-info/metadata.json
jucycru-0.4.2.dist-info/top_level.txt
