Metadata-Version: 2.0
Name: jucycru
Version: 0.4.2
Summary: JUICE cruise phase package
Home-page: https://bitbucket.org/btorn/jucycru
Author: Benjamin Torn
Author-email: btorn@cosmos.esa.int
License: MIT
Platform: UNKNOWN
Requires-Dist: matplotlib
Requires-Dist: numpy
Requires-Dist: spiceypy
